{
  "received_unique": 1999,
  "recv_total": 1999,
  "total_expected": 2000,
  "delivery_rate": 0.9995,
  "duplicate_rate": 0.0,
  "duplicates": 0,
  "out_of_order": 158,
  "lagged_events": 0,
  "lat_min": 33,
  "lat_p50": 106,
  "lat_p90": 323,
  "lat_p99": 606,
  "lat_max": 2709,
  "ldh_min": 0,
  "ldh_p50": 0,
  "ldh_p90": 1,
  "ldh_p99": 4,
  "ldh_max": 6,
  "pr_avg_ratio": 1.0,
  "avg_connected_peers": 2.6067067575469163,
  "downtime_total_ms": 1687,
  "downtime_periods": 1,
  "downtime_p50_ms": 1687,
  "downtime_p90_ms": 1687,
  "downtime_max_ms": 1687,
  "neighbour_down": 14,
  "neighbour_up": 17,
  "joined": true,
  "join_wait_ms": 1564,
  "saw_test": true,
  "timed_out_no_data": false
}
