{
  "received_unique": 1999,
  "recv_total": 1999,
  "total_expected": 2000,
  "delivery_rate": 0.9995,
  "duplicate_rate": 0.0,
  "duplicates": 0,
  "out_of_order": 339,
  "lagged_events": 0,
  "lat_min": 85,
  "lat_p50": 380,
  "lat_p90": 680,
  "lat_p99": 1014,
  "lat_max": 3798,
  "ldh_min": 1,
  "ldh_p50": 2,
  "ldh_p90": 4,
  "ldh_p99": 6,
  "ldh_max": 7,
  "convergence_time_ms": null,
  "pr_avg_ratio": 1.0,
  "rt_avg_ms": 3640,
  "rt_p50_ms": 1319,
  "rt_p90_ms": 15172,
  "rt_max_ms": 15172,
  "disconnect_events": 6,
  "reconnect_events": 5,
  "reconnect_samples": 5,
  "joined": true,
  "join_wait_ms": 1537,
  "saw_test": true,
  "timed_out_no_data": false
}
