{
  "received_unique": 1999,
  "recv_total": 1999,
  "total_expected": 2000,
  "delivery_rate": 0.9995,
  "duplicate_rate": 0.0,
  "duplicates": 0,
  "out_of_order": 361,
  "lagged_events": 0,
  "lat_min": 39,
  "lat_p50": 253,
  "lat_p90": 498,
  "lat_p99": 11481,
  "lat_max": 13367,
  "ldh_min": 1,
  "ldh_p50": 4,
  "ldh_p90": 6,
  "ldh_p99": 9,
  "ldh_max": 11,
  "pr_avg_ratio": 1.0,
  "avg_connected_peers": 1.5868813698209194,
  "downtime_total_ms": 109,
  "downtime_periods": 1,
  "downtime_p50_ms": 109,
  "downtime_p90_ms": 109,
  "downtime_max_ms": 109,
  "neighbour_down": 10,
  "neighbour_up": 12,
  "joined": true,
  "join_wait_ms": 1591,
  "saw_test": true,
  "timed_out_no_data": false
}
