{
  "received_unique": 1985,
  "recv_total": 1985,
  "total_expected": 2000,
  "delivery_rate": 0.9925,
  "duplicate_rate": 0.0,
  "duplicates": 0,
  "out_of_order": 213,
  "lagged_events": 0,
  "lat_min": 33,
  "lat_p50": 144,
  "lat_p90": 340,
  "lat_p99": 585,
  "lat_max": 1305,
  "ldh_min": 0,
  "ldh_p50": 0,
  "ldh_p90": 1,
  "ldh_p99": 3,
  "ldh_max": 5,
  "convergence_time_ms": null,
  "pr_avg_ratio": 1.0,
  "rt_avg_ms": 1529,
  "rt_p50_ms": 1511,
  "rt_p90_ms": 2958,
  "rt_max_ms": 2958,
  "disconnect_events": 3,
  "reconnect_events": 3,
  "reconnect_samples": 3,
  "joined": true,
  "join_wait_ms": 5243,
  "saw_test": true,
  "timed_out_no_data": false
}
