{
  "received_unique": 2000,
  "recv_total": 2000,
  "total_expected": 2000,
  "delivery_rate": 1.0,
  "duplicate_rate": 0.0,
  "duplicates": 0,
  "out_of_order": 118,
  "lagged_events": 0,
  "lat_min": 0,
  "lat_p50": 133,
  "lat_p90": 328,
  "lat_p99": 530,
  "lat_max": 748,
  "ldh_min": 0,
  "ldh_p50": 1,
  "ldh_p90": 2,
  "ldh_p99": 3,
  "ldh_max": 4,
  "convergence_time_ms": 202320,
  "pr_avg_ratio": 1.0,
  "rt_avg_ms": 96,
  "rt_p50_ms": 57,
  "rt_p90_ms": 375,
  "rt_max_ms": 375,
  "disconnect_events": 8,
  "reconnect_events": 7,
  "reconnect_samples": 6,
  "joined": true,
  "join_wait_ms": 3734,
  "saw_test": true,
  "timed_out_no_data": false
}
